{"numeroLinea":"30","destinos":["LAS FUENTES",null],"paradas1":[{"id":"632","destino":"LAS FUENTES","nombre":" PS CONSTITUCIÓN 11 "},{"id":"707","destino":"LAS FUENTES","nombre":" PZA ARAGÓN "},{"id":"719","destino":"LAS FUENTES","nombre":" PZA ESPAÑA "},{"id":"745","destino":"LAS FUENTES","nombre":" PLZ SAN MIGUEL "},{"id":"3026","destino":"LAS FUENTES","nombre":" J. COCCI "},{"id":"3015","destino":"LAS FUENTES","nombre":" C. DE CASPE 26 "},{"id":"313","destino":"LAS FUENTES","nombre":" C. DE CASPE 48 "},{"id":"760","destino":"LAS FUENTES","nombre":" S. MINGUIJÓN 10 "},{"id":"3020","destino":"LAS FUENTES","nombre":" S. MINGUIJÓN 28 / AMISTAD "},{"id":"1074","destino":"LAS FUENTES","nombre":" SALVADOR MINGUIJÓN 64 "},{"id":"460","destino":"LAS FUENTES","nombre":" DOCTOR IRANZO / AZORIN "},{"id":"430","destino":"LAS FUENTES","nombre":" DOCTOR IRANZO 61 "},{"id":"753","destino":"LAS FUENTES","nombre":" ROD REBOLLEDO 7 "},{"id":"532","destino":"LAS FUENTES","nombre":" J. COCCI 21 "},{"id":"20","destino":"LAS FUENTES","nombre":" ASALTO 63 "},{"id":"1248","destino":"LAS FUENTES","nombre":" Ps LA MINA 15 "},{"id":"634","destino":"LAS FUENTES","nombre":" PS CONSTITUCIÓN 33 "}],"paradas2":[]}